passwd_checker/__init__.py
passwd_checker/checker.py
passwd_checker/data/common-credentials-100k.txt
passwd_checker/data/common-credentials-10k.txt
passwd_checker/data/common-credentials-1M.txt
passwd_checker/data/common-credentials-1k.txt
passwd_checker-0.0.1.dist-info/LICENSE
passwd_checker-0.0.1.dist-info/METADATA
passwd_checker-0.0.1.dist-info/WHEEL
passwd_checker-0.0.1.dist-info/top_level.txt
passwd_checker-0.0.1.dist-info/RECORD
